Workbook

Sheet Read Me
A1: Car Rental Company Workbook
A2: Sample data in LKR and km. Replace the sample rows with your own.
A4: Colour legend
A5: Blue text = input you type (IDs, rates, days, amounts, readings).
A6: Black text = formula (do not type over).
A7: Green text = value pulled from another sheet.
A9: How the sheets link
A10: Owners -> Vehicles (Owner ID) -> Rentals (Vehicle No) <- Renters (Renter ID).
A11: Maintenance feeds Vehicles (cost this month) and Owner Payments (deduction).
A12: Owner Payments and Renter Receipts are calculated from Rentals. You only type Amount Paid / Amount Received.
A13: Monthly Summary adds everything up by month.
A15: Adding new rows
... A24: Month is stored as text like 'Oct 2026' and must match exactly across sheets.

Sheet Owners
A1: Owner ID | B1: Owner Name | C1: Phone | D1: Bank Account
A2: O01 | B2: Mr. Perera | C2: 077 111 1111 | D2: 1234567
A3: O02 | B3: Mrs. Silva | C3: 071 222 2222 | D3: 2345678
A4: O03 | B4: Mr. Fernando | C4: 070 333 3333 | D4: 3456789

Sheet Vehicles
A1: Vehicle No | B1: Vehicle | C1: Owner ID | D1: Owner Name | E1: Rate Paid to Owner (per day) | F1: Rate Charged to Renter (per day) | G1: Odometer Start of Month (km) | H1: Odometer End of Month (km) | I1: Mileage This Month (km) | J1: Total Mileage (km) | K1: Maintenance Type | L1: Last Service Date | M1: Mileage at Last Service (km) | N1: Service Interval (km) | O1: Maintenance Cost This Month | P1: Who Bears Cost | Q1: Next Service Due (Date) | R1: Next Service Due (km) | S1: Service Status
A2: V001 | B2: Toyota Axio | C2: O01 | D2: =INDEX(Owners!$B$2:$B$200,MATCH(C2,Owners!$A$2:$A$200,0)) -> Mr. Perera | E2: 6000 | F2: 8000 | G2: 45200 | H2: 46100 | I2: =H2-G2 -> 900 | J2: =H2 -> 46100 | K2: Oil change | L2: 46300 | M2: 45500 | N2: 5000 | O2: =SUMIFS(Maintenance!$E$2:$E$200,Maintenance!$B$2:$B$200,A2,Maintenance!$C$2:$C$200,'Monthly Summary'!$A$2) -> 2000 | P2: Owner (deducted) | Q2: 46392 | R2: =M2+N2 -> 50500 | S2: =IF(J2>=R2,"SERVICE OVERDUE",IF(R2-J2<=500,"Service due soon","OK")) -> OK
A3: V002 | B3: Suzuki Wagon R | C3: O02 | D3: =INDEX(Owners!$B$2:$B$200,MATCH(C3,Owners!$A$2:$A$200,0)) -> Mrs. Silva | E3: 4000 | F3: 5500 | G3: 31000 | H3: 32300 | I3: =H3-G3 -> 1300 | J3: =H3 -> 32300 | K3: Tyre repair | L3: 46307 | M3: 31600 | N3: 10000 | O3: =SUMIFS(Maintenance!$E$2:$E$200,Maintenance!$B$2:$B$200,A3,Maintenance!$C$2:$C$200,'Monthly Summary'!$A$2) -> 3000 | P3: Owner (deducted) | Q3: 46489 | R3: =M3+N3 -> 41600 | S3: =IF(J3>=R3,"SERVICE OVERDUE",IF(R3-J3<=500,"Service due soon","OK")) -> OK
A4: V003 | B4: Nissan Caravan | C4: O03 | D4: =INDEX(Owners!$B$2:$B$200,MATCH(C4,Owners!$A$2:$A$200,0)) -> Mr. Fernando | E4: 9000 | F4: 12000 | G4: 78400 | H4: 80200 | I4: =H4-G4 -> 1800 | J4: =H4 -> 80200 | K4: Brake service | L4: 46313 | M4: 79100 | N4: 10000 | O4: =SUMIFS(Maintenance!$E$2:$E$200,Maintenance!$B$2:$B$200,A4,Maintenance!$C$2:$C$200,'Monthly Summary'!$A$2) -> 5000 | P4: Owner (deducted) | Q4: 46495 | R4: =M4+N4 -> 89100 | S4: =IF(J4>=R4,"SERVICE OVERDUE",IF(R4-J4<=500,"Service due soon","OK")) -> OK
A6: TOTAL | I6: =SUM(I2:I5) -> 4000 | O6: =SUM(O2:O5) -> 10000
A8: Maintenance cost this month is for the month typed in 'Monthly Summary'!A2 (Oct 2026). 'Service due soon' = within 500 km of next service (assumption).
A9: Mileage columns G and H are for the same month as above; update them each month.

Sheet Renters
A1: Renter ID | B1: Name | C1: Type | D1: Phone
A2: R01 | B2: Nimal | C2: Person | D2: 077 444 4444
A3: R02 | B3: Kamal Ltd | C3: Company | D3: 011 555 5555
A4: R03 | B4: ABC Travels | C4: Company | D4: 011 666 6666

Sheet Companies
A1: Company ID | B1: Renter ID | C1: Company Name | D1: Contact Person | E1: Phone | F1: Email | G1: Address | H1: Payment Terms (days) | I1: Total Billed | J1: Amount Received | K1: Cash Still to Receive
A2: C01 | B2: R02 | C2: =INDEX(Renters!$B$2:$B$200,MATCH(B2,Renters!$A$2:$A$200,0)) -> Kamal Ltd | D2: Mr. Jayasuriya | E2: 011 555 5555 | F2: accounts@kamal.example | G2: Colombo 03 | H2: 30 | I2: =SUMIFS('Renter Receipts'!$G$2:$G$200,'Renter Receipts'!$C$2:$C$200,C2) -> 82500 | J2: =SUMIFS('Renter Receipts'!$H$2:$H$200,'Renter Receipts'!$C$2:$C$200,C2) -> 82500 | K2: =I2-J2 -> 0
A3: C02 | B3: R03 | C3: =INDEX(Renters!$B$2:$B$200,MATCH(B3,Renters!$A$2:$A$200,0)) -> ABC Travels | D3: Ms. Fonseka | E3: 011 666 6666 | F3: finance@abctravels.example | G3: Kandy | H3: 14 | I3: =SUMIFS('Renter Receipts'!$G$2:$G$200,'Renter Receipts'!$C$2:$C$200,C3) -> 240000 | J3: =SUMIFS('Renter Receipts'!$H$2:$H$200,'Renter Receipts'!$C$2:$C$200,C3) -> 100000 | K3: =I3-J3 -> 140000
A5: TOTAL | I5: =SUM(I2:I4) -> 322500 | J5: =SUM(J2:J4) -> 182500 | K5: =SUM(K2:K4) -> 140000
A7: Company ID, contact details and payment terms are sample data. Renter ID must match a Company in the Renters sheet; totals cover all months.

Sheet Rentals
A1: Rental ID | B1: Vehicle No | C1: Renter ID | D1: Month | E1: Days Rented
A2: RT01 | B2: V001 | C2: R01 | D2: Oct 2026 | E2: 10
A3: RT02 | B3: V002 | C3: R02 | D3: Oct 2026 | E3: 15
A4: RT03 | B4: V003 | C4: R03 | D4: Oct 2026 | E4: 20
A6: TOTAL | E6: =SUM(E2:E5) -> 45

Sheet Maintenance
A1: Maint ID | B1: Vehicle No | C1: Month | D1: Description | E1: Cost (LKR)
A2: M01 | B2: V001 | C2: Oct 2026 | D2: Oil change | E2: 2000
A3: M02 | B3: V002 | C3: Oct 2026 | D3: Tyre repair | E3: 3000
A4: M03 | B4: V003 | C4: Oct 2026 | D4: Brake service | E4: 5000
A6: TOTAL | E6: =SUM(E2:E5) -> 10000

Sheet Owner Payments
A1: Rental ID | B1: Vehicle No | C1: Owner | D1: Month | E1: Days | F1: Rate Paid to Owner (per day) | G1: Gross Pay | H1: Maintenance Deduction | I1: Net Pay | J1: Amount Paid | K1: Still to Pay
A2: =Rentals!A2 -> RT01 | B2: =Rentals!B2 -> V001 | C2: =INDEX(Vehicles!$D$2:$D$5,MATCH(B2,Vehicles!$A$2:$A$5,0)) -> Mr. Perera | D2: =Rentals!D2 -> Oct 2026 | E2: =Rentals!E2 -> 10 | F2: =INDEX(Vehicles!$E$2:$E$5,MATCH(B2,Vehicles!$A$2:$A$5,0)) -> 6000 | G2: =E2*F2 -> 60000 | H2: =IF(INDEX(Vehicles!$P$2:$P$5,MATCH(B2,Vehicles!$A$2:$A$5,0))="Owner (deducted)",SUMIFS(Maintenance!$E$2:$E$200,Maintenance!$B$2:$B$200,B2,Maintenance!$C$2:$C$200,D2),0) -> 2000 | I2: =G2-H2 -> 58000 | J2: 58000 | K2: =I2-J2 -> 0
A3: =Rentals!A3 -> RT02 | B3: =Rentals!B3 -> V002 | C3: =INDEX(Vehicles!$D$2:$D$5,MATCH(B3,Vehicles!$A$2:$A$5,0)) -> Mrs. Silva | D3: =Rentals!D3 -> Oct 2026 | E3: =Rentals!E3 -> 15 | F3: =INDEX(Vehicles!$E$2:$E$5,MATCH(B3,Vehicles!$A$2:$A$5,0)) -> 4000 | G3: =E3*F3 -> 60000 | H3: =IF(INDEX(Vehicles!$P$2:$P$5,MATCH(B3,Vehicles!$A$2:$A$5,0))="Owner (deducted)",SUMIFS(Maintenance!$E$2:$E$200,Maintenance!$B$2:$B$200,B3,Maintenance!$C$2:$C$200,D3),0) -> 3000 | I3: =G3-H3 -> 57000 | J3: 30000 | K3: =I3-J3 -> 27000
A4: =Rentals!A4 -> RT03 | B4: =Rentals!B4 -> V003 | C4: =INDEX(Vehicles!$D$2:$D$5,MATCH(B4,Vehicles!$A$2:$A$5,0)) -> Mr. Fernando | D4: =Rentals!D4 -> Oct 2026 | E4: =Rentals!E4 -> 20 | F4: =INDEX(Vehicles!$E$2:$E$5,MATCH(B4,Vehicles!$A$2:$A$5,0)) -> 9000 | G4: =E4*F4 -> 180000 | H4: =IF(INDEX(Vehicles!$P$2:$P$5,MATCH(B4,Vehicles!$A$2:$A$5,0))="Owner (deducted)",SUMIFS(Maintenance!$E$2:$E$200,Maintenance!$B$2:$B$200,B4,Maintenance!$C$2:$C$200,D4),0) -> 5000 | I4: =G4-H4 -> 175000 | J4: 0 | K4: =I4-J4 -> 175000
A5: TOTAL | E5: =SUM(E2:E4) -> 45 | G5: =SUM(G2:G4) -> 300000 | H5: =SUM(H2:H4) -> 10000 | I5: =SUM(I2:I4) -> 290000 | J5: =SUM(J2:J4) -> 88000 | K5: =SUM(K2:K4) -> 202000

Sheet Renter Receipts
A1: Rental ID | B1: Vehicle No | C1: Renter | D1: Month | E1: Days | F1: Rate Charged to Renter (per day) | G1: Total Billed | H1: Amount Received | I1: Cash Still to Receive
A2: =Rentals!A2 -> RT01 | B2: =Rentals!B2 -> V001 | C2: =INDEX(Renters!$B$2:$B$200,MATCH(Rentals!C2,Renters!$A$2:$A$200,0)) -> Nimal | D2: =Rentals!D2 -> Oct 2026 | E2: =Rentals!E2 -> 10 | F2: =INDEX(Vehicles!$F$2:$F$5,MATCH(B2,Vehicles!$A$2:$A$5,0)) -> 8000 | G2: =E2*F2 -> 80000 | H2: 50000 | I2: =G2-H2 -> 30000
A3: =Rentals!A3 -> RT02 | B3: =Rentals!B3 -> V002 | C3: =INDEX(Renters!$B$2:$B$200,MATCH(Rentals!C3,Renters!$A$2:$A$200,0)) -> Kamal Ltd | D3: =Rentals!D3 -> Oct 2026 | E3: =Rentals!E3 -> 15 | F3: =INDEX(Vehicles!$F$2:$F$5,MATCH(B3,Vehicles!$A$2:$A$5,0)) -> 5500 | G3: =E3*F3 -> 82500 | H3: 82500 | I3: =G3-H3 -> 0
A4: =Rentals!A4 -> RT03 | B4: =Rentals!B4 -> V003 | C4: =INDEX(Renters!$B$2:$B$200,MATCH(Rentals!C4,Renters!$A$2:$A$200,0)) -> ABC Travels | D4: =Rentals!D4 -> Oct 2026 | E4: =Rentals!E4 -> 20 | F4: =INDEX(Vehicles!$F$2:$F$5,MATCH(B4,Vehicles!$A$2:$A$5,0)) -> 12000 | G4: =E4*F4 -> 240000 | H4: 100000 | I4: =G4-H4 -> 140000
A5: TOTAL | E5: =SUM(E2:E4) -> 45 | G5: =SUM(G2:G4) -> 402500 | H5: =SUM(H2:H4) -> 232500 | I5: =SUM(I2:I4) -> 170000

Sheet Monthly Summary
A1: Month | B1: Total Billed | C1: Received | D1: Still to Receive | E1: Owner Net Pay | F1: Paid to Owners | G1: Still to Pay Owners | H1: Our Profit (Billed - Owner Net Pay) | I1: Cash Position (Received - Paid to Owners)
A2: Oct 2026 | B2: =SUMIFS('Renter Receipts'!$G$2:$G$200,'Renter Receipts'!$D$2:$D$200,A2) -> 402500 | C2: =SUMIFS('Renter Receipts'!$H$2:$H$200,'Renter Receipts'!$D$2:$D$200,A2) -> 232500 | D2: =B2-C2 -> 170000 | E2: =SUMIFS('Owner Payments'!$I$2:$I$200,'Owner Payments'!$D$2:$D$200,A2) -> 290000 | F2: =SUMIFS('Owner Payments'!$J$2:$J$200,'Owner Payments'!$D$2:$D$200,A2) -> 88000 | G2: =E2-F2 -> 202000 | H2: =B2-E2 -> 112500 | I2: =C2-F2 -> 144500
A3: Nov 2026 | B3: =SUMIFS('Renter Receipts'!$G$2:$G$200,'Renter Receipts'!$D$2:$D$200,A3) -> 0 | C3: =SUMIFS('Renter Receipts'!$H$2:$H$200,'Renter Receipts'!$D$2:$D$200,A3) -> 0 | D3: =B3-C3 -> 0 | E3: =SUMIFS('Owner Payments'!$I$2:$I$200,'Owner Payments'!$D$2:$D$200,A3) -> 0 | F3: =SUMIFS('Owner Payments'!$J$2:$J$200,'Owner Payments'!$D$2:$D$200,A3) -> 0 | G3: =E3-F3 -> 0 | H3: =B3-E3 -> 0 | I3: =C3-F3 -> 0
A4: Dec 2026 | B4: =SUMIFS('Renter Receipts'!$G$2:$G$200,'Renter Receipts'!$D$2:$D$200,A4) -> 0 | C4: =SUMIFS('Renter Receipts'!$H$2:$H$200,'Renter Receipts'!$D$2:$D$200,A4) -> 0 | D4: =B4-C4 -> 0 | E4: =SUMIFS('Owner Payments'!$I$2:$I$200,'Owner Payments'!$D$2:$D$200,A4) -> 0 | F4: =SUMIFS('Owner Payments'!$J$2:$J$200,'Owner Payments'!$D$2:$D$200,A4) -> 0 | G4: =E4-F4 -> 0 | H4: =B4-E4 -> 0 | I4: =C4-F4 -> 0
A5: TOTAL | B5: =SUM(B2:B4) -> 402500 | C5: =SUM(C2:C4) -> 232500 | D5: =SUM(D2:D4) -> 170000 | E5: =SUM(E2:E4) -> 290000 | F5: =SUM(F2:F4) -> 88000 | G5: =SUM(G2:G4) -> 202000 | H5: =SUM(H2:H4) -> 112500 | I5: =SUM(I2:I4) -> 144500
